lulzprime/__init__.py
lulzprime/__main__ 2.py
lulzprime/__main__.py
lulzprime/batch.py
lulzprime/cli 2.py
lulzprime/cli.py
lulzprime/config.py
lulzprime/diagnostics.py
lulzprime/forecast.py
lulzprime/gaps.py
lulzprime/lehmer.py
lulzprime/lookup.py
lulzprime/pi.py
lulzprime/primality.py
lulzprime/resolve.py
lulzprime/simulator.py
lulzprime/types.py
lulzprime/utils.py
lulzprime-0.2.0.dist-info/licenses/LICENSE
lulzprime-0.2.0.dist-info/METADATA
lulzprime-0.2.0.dist-info/WHEEL
lulzprime-0.2.0.dist-info/top_level.txt
lulzprime-0.2.0.dist-info/RECORD
