Metadata-Version: 2.4
Name: lulzprime
Version: 0.2.0
Summary: Prime resolution and navigation library based on OMPC
Author-email: RobLe <github@roblemumin.com>
License-Expression: MIT
Project-URL: Homepage, https://github.com/RobLe3/lulzprime
Project-URL: Repository, https://github.com/RobLe3/lulzprime
Project-URL: Documentation, https://github.com/RobLe3/lulzprime/tree/main/docs
Project-URL: Issues, https://github.com/RobLe3/lulzprime/issues
Keywords: primes,mathematics,number-theory,OMPC
Classifier: Development Status :: 3 - Alpha
Classifier: Intended Audience :: Science/Research
Classifier: Intended Audience :: Developers
Classifier: Programming Language :: Python :: 3
Classifier: Programming Language :: Python :: 3.10
Classifier: Programming Language :: Python :: 3.11
Classifier: Programming Language :: Python :: 3.12
Classifier: Topic :: Scientific/Engineering :: Mathematics
Requires-Python: >=3.10
License-File: LICENSE
Provides-Extra: dev
Requires-Dist: pytest>=7.0; extra == "dev"
Requires-Dist: pytest-cov>=4.0; extra == "dev"
Requires-Dist: black>=23.0; extra == "dev"
Requires-Dist: mypy>=1.0; extra == "dev"
Requires-Dist: ruff>=0.1.0; extra == "dev"
Provides-Extra: docs
Requires-Dist: mkdocs>=1.5; extra == "docs"
Requires-Dist: mkdocs-material>=9.0; extra == "docs"
Dynamic: license-file
